pyMathBitPrecise/__init__.py
pyMathBitPrecise/array3t.py
pyMathBitPrecise/bit_utils.py
pyMathBitPrecise/bits3t.py
pyMathBitPrecise/bits3t_vld_masks.py
pyMathBitPrecise/enum3t.py
pyMathBitPrecise/utils.py
pyMathBitPrecise-0.9.dist-info/LICENSE
pyMathBitPrecise-0.9.dist-info/METADATA
pyMathBitPrecise-0.9.dist-info/WHEEL
pyMathBitPrecise-0.9.dist-info/top_level.txt
pyMathBitPrecise-0.9.dist-info/RECORD
