Metadata-Version: 2.1
Name: pyMathBitPrecise
Version: 0.9
Summary: number types of variable bit size and utils for bit manipulations
Home-page: https://github.com/Nic30/pyMathBitPrecise
Author: Michal Orsak
Author-email: michal.o.socials@gmail.com
License: MIT
Platform: UNKNOWN
Classifier: Development Status :: 4 - Beta
Classifier: Intended Audience :: Developers
Classifier: License :: OSI Approved :: MIT License
Classifier: Operating System :: OS Independent
Classifier: Programming Language :: Python :: 3
Classifier: Programming Language :: Python :: 3.6
Classifier: Programming Language :: Python :: 3.7
Classifier: Programming Language :: Python :: 3.8
Classifier: Programming Language :: Python :: 3.9
Classifier: Topic :: Scientific/Engineering :: Electronic Design Automation (EDA)
Classifier: Topic :: System :: Hardware
Classifier: Topic :: System :: Emulators
Classifier: Topic :: Utilities
